Metadata-Version: 1.0
Name: password-helper
Version: 0.1
Summary: password generator
Home-page: UNKNOWN
Author: UNKNOWN
Author-email: UNKNOWN
License: UNKNOWN
Platform: UNKNOWN
